MANIFEST.in
requirements.txt
setup.py
bin/wm-reader
bin/wm-writer
src/watermarks/__init__.py
src/watermarks/selftest.py
src/watermarks.egg-info/PKG-INFO
src/watermarks.egg-info/SOURCES.txt
src/watermarks.egg-info/dependency_links.txt
src/watermarks.egg-info/requires.txt
src/watermarks.egg-info/top_level.txt
src/watermarks/bin/__init__.py
src/watermarks/core/__init__.py
src/watermarks/core/loader.py
src/watermarks/core/method.py
src/watermarks/core/utils.py
src/watermarks/core/watermark.py
src/watermarks/core/readers/__init__.py
src/watermarks/core/readers/lsb.py
src/watermarks/core/writers/__init__.py
src/watermarks/core/writers/lsb.py
src/watermarks/core/writers/visible.py