Metadata-Version: 1.0
Name: watermarks
Version: 0.4
Summary: Do you want to protect your pictures? Or do you want to include information into your pictures (e.g. to who it was delivered)? Then this library is designed right for you! Currently visible and LSB watermark methods are supported. You can also add your own protection methods.
Home-page: https://github.com/vladozc/watermarks
Author: Vladimir Chovanec
Author-email: watermarks.py@gmail.com
License: UNKNOWN
Keywords: watermark,watermarks,watermarker,watermarking,lsb
Platform: UNKNOWN
Classifier: Development Status :: 4 - Beta
Classifier: Environment :: Console
Classifier: Intended Audience :: Developers
Classifier: License :: OSI Approved :: GNU General Public License (GPL)
Classifier: Natural Language :: English
Classifier: Operating System :: OS Independent
Classifier: Programming Language :: Python
Classifier: Programming Language :: Python :: 2.6
Classifier: Programming Language :: Python :: 2.7
Classifier: Programming Language :: Python :: 3
Classifier: Programming Language :: Python :: 3.2
Classifier: Programming Language :: Python :: 3.3
Classifier: Programming Language :: Python :: 3.4
Classifier: Topic :: Software Development :: Libraries :: Python Modules
Classifier: Topic :: Multimedia :: Graphics
